nbdev_mkdocs/__init__.py
nbdev_mkdocs/_cli.py
nbdev_mkdocs/_modidx.py
nbdev_mkdocs/_package_data.py
nbdev_mkdocs/_testing.py
nbdev_mkdocs/docstring.py
nbdev_mkdocs/mkdocs.py
nbdev_mkdocs/social_image_generator.py
nbdev_mkdocs/_helpers/__init__.py
nbdev_mkdocs/_helpers/cli_doc.py
nbdev_mkdocs/_helpers/utils.py
nbdev_mkdocs/package_data/changelog_not_found.md
nbdev_mkdocs/package_data/cli_commands_not_found.md
nbdev_mkdocs/package_data/custom-social-image-template.html
nbdev_mkdocs/package_data/ghp_deploy_action_template.yml
nbdev_mkdocs/package_data/gitignore.txt
nbdev_mkdocs/package_data/mkdocs_template.yml
nbdev_mkdocs/package_data/requirements.txt
nbdev_mkdocs/package_data/mkdocs_template/docs_overrides/css/extra.css
nbdev_mkdocs/package_data/mkdocs_template/docs_overrides/images/compass-outline.png
nbdev_mkdocs/package_data/mkdocs_template/docs_overrides/images/default_social_logo.png
nbdev_mkdocs/package_data/mkdocs_template/docs_overrides/js/extra.js
nbdev_mkdocs/package_data/mkdocs_template/docs_overrides/js/math.js
nbdev_mkdocs/package_data/mkdocs_template/docs_overrides/js/mathjax.js
nbdev_mkdocs/package_data/mkdocs_template/overrides/main.html
nbdev_mkdocs/package_data/mkdocs_template/site_overrides/main.html
nbdev_mkdocs/package_data/mkdocs_template/site_overrides/partials/copyright.html
nbdev_mkdocs-1.0.0.dist-info/LICENSE
nbdev_mkdocs-1.0.0.dist-info/METADATA
nbdev_mkdocs-1.0.0.dist-info/WHEEL
nbdev_mkdocs-1.0.0.dist-info/entry_points.txt
nbdev_mkdocs-1.0.0.dist-info/top_level.txt
nbdev_mkdocs-1.0.0.dist-info/RECORD
