Metadata-Version: 2.1
Name: nbdev-mkdocs
Version: 1.0.0
Summary: Extension of nbdev for generating documentation using Material for Mkdocs instead of Quarto
Home-page: https://github.com/airtai/nbdev-mkdocs
Author: airt
Author-email: info@airt.ai
License: Apache Software License 2.0
Keywords: nbdev jupyter notebook python mkdocs material
Classifier: Development Status :: 4 - Beta
Classifier: Intended Audience :: Developers
Classifier: Natural Language :: English
Classifier: Programming Language :: Python :: 3.7
Classifier: Programming Language :: Python :: 3.8
Classifier: Programming Language :: Python :: 3.9
Classifier: Programming Language :: Python :: 3.10
Classifier: License :: OSI Approved :: Apache Software License
Requires-Python: >=3.7
License-File: LICENSE
Requires-Dist: nbdev (>=2.3.9)
Requires-Dist: typer[all] (>=0.7.0)
Requires-Dist: mkdocs (>=1.4.2)
Requires-Dist: mkdocstrings (==0.18.1)
Requires-Dist: mkdocs-material (>=8.5.11)
Requires-Dist: mkdocs-literate-nav (>=0.5.0)
Requires-Dist: mkdocs-section-index (>=0.3.4)
Requires-Dist: configupdater (>=3.1.1)
Requires-Dist: griffe (>=0.24.1)
Requires-Dist: ruamel.yaml (>=0.17.21)
Requires-Dist: openai (>=0.25.0)
Requires-Dist: playwright (>=1.28.0)
Requires-Dist: docstring-gen (>=0.2.0)
Requires-Dist: mypy-extensions (>=0.4.3)
Provides-Extra: dev
Requires-Dist: bandit (>=1.7.4) ; extra == 'dev'
Requires-Dist: semgrep (>=0.115.0) ; extra == 'dev'
Requires-Dist: pytest (>=7.1.3) ; extra == 'dev'
Requires-Dist: numpy (>=1.0) ; extra == 'dev'
Requires-Dist: black (>=22.8.0) ; extra == 'dev'
Requires-Dist: mypy (>=0.960) ; extra == 'dev'
Requires-Dist: nbqa (>=1.5.3) ; extra == 'dev'
Requires-Dist: isort (>=5.11.4) ; extra == 'dev'
Requires-Dist: pre-commit (>=2.21.0) ; extra == 'dev'
